geobinning/__init__.py
geobinning-2.0.1.dist-info/METADATA
geobinning-2.0.1.dist-info/WHEEL
geobinning-2.0.1.dist-info/top_level.txt
geobinning-2.0.1.dist-info/RECORD
