Metadata-Version: 2.1
Name: geobinning
Version: 2.0.1
Summary: A package to bin coordinate data in geojson shapes.
Home-page: https://kapastor.github.io/
Author: Kyle Pastor
Author-email: kyleanthonypastor@gmail.com
License: MIT
Platform: UNKNOWN
Classifier: License :: OSI Approved :: MIT License
Classifier: Programming Language :: Python :: 3
Classifier: Programming Language :: Python :: 3.7
Requires-Dist: matplotlib
Requires-Dist: numpy
Requires-Dist: pandas
